pairless/__init__.py
pairless/pipe.py
pairless-0.0.8.dist-info/LICENSE
pairless-0.0.8.dist-info/METADATA
pairless-0.0.8.dist-info/WHEEL
pairless-0.0.8.dist-info/top_level.txt
pairless-0.0.8.dist-info/RECORD
