Metadata-Version: 2.1
Name: pairless
Version: 0.0.8
Summary: use >> replace pair ,such as `group_by_slice(lst,2)  lst>>group_by_slice(2)`
Home-page: https://github.com/Hexmagic/pairless.git
Author: hexmagic
Author-email: 191440042@qq.com
Maintainer: hexmagic
License: BSD License
Platform: all
Classifier: Development Status :: 4 - Beta
Classifier: Operating System :: OS Independent
Classifier: Intended Audience :: Developers
Classifier: License :: OSI Approved :: BSD License
Classifier: Programming Language :: Python
Classifier: Programming Language :: Python :: Implementation
Classifier: Programming Language :: Python :: 2
Classifier: Programming Language :: Python :: 2.7
Classifier: Programming Language :: Python :: 3
Classifier: Programming Language :: Python :: 3.4
Classifier: Programming Language :: Python :: 3.5
Classifier: Programming Language :: Python :: 3.6
Classifier: Topic :: Software Development :: Libraries
